tree_sitter_strudel/__init__.pyi
tree_sitter_strudel/binding.c
tree_sitter_strudel/__init__.py
tree_sitter_strudel/py.typed
tree_sitter_strudel/_binding.abi3.so
tree_sitter_strudel/queries/highlights.scm
tree_sitter_strudel-1.1.8.dist-info/RECORD
tree_sitter_strudel-1.1.8.dist-info/WHEEL
tree_sitter_strudel-1.1.8.dist-info/top_level.txt
tree_sitter_strudel-1.1.8.dist-info/METADATA
tree_sitter_strudel-1.1.8.dist-info/licenses/LICENSE
